pyramid_force_https
