Metadata-Version: 1.1
Name: pyramid-force-https
Version: 0.1.1
Summary: A tween to force HTTPS.
Home-page: https://github.com/niteoweb/pyramid_force_https
Author: NiteoWeb Ltd.
Author-email: info@niteoweb.com
License: BSD
Keywords: pyramid ssl pylons web
Platform: UNKNOWN
Classifier: Operating System :: OS Independent
Classifier: License :: OSI Approved :: BSD License
Classifier: Programming Language :: Python
Classifier: Development Status :: 4 - Beta
Classifier: Intended Audience :: Developers
Classifier: Framework :: Pylons
Classifier: Topic :: Internet :: WWW/HTTP
Classifier: Topic :: Internet :: WWW/HTTP :: WSGI
Classifier: Topic :: Software Development :: Libraries :: Python Modules
